tkitAutoMark/__init__.py
tkitAutoMark/automark.py
tkitAutoMark-0.0.0.1.4.dist-info/LICENSE
tkitAutoMark-0.0.0.1.4.dist-info/METADATA
tkitAutoMark-0.0.0.1.4.dist-info/WHEEL
tkitAutoMark-0.0.0.1.4.dist-info/top_level.txt
tkitAutoMark-0.0.0.1.4.dist-info/RECORD
