Metadata-Version: 2.1
Name: tkitAutoMark
Version: 0.0.0.1.4
Summary: Terry toolkit tkitAutoMark
Home-page: https://github.com/napoler/tkitAutoMark-pytorch
Author: Terry Chan
Author-email: napoler2008@gmail.com
License: UNKNOWN
Platform: UNKNOWN
Requires-Dist: pytorch-lightning (>=1.2.10)
Requires-Dist: pytorch-crf (>=0.7.2)
Requires-Dist: performer-pytorch (>=1.0.11)
Requires-Dist: tkit-transformer-xl (>=0.0.0.6)
Requires-Dist: tkit-mlp-pytorch (>=0.0.0.1)
Requires-Dist: memory-transformer-xl (>=0.1.0)
Requires-Dist: tkitbilstm (>=0.0.0.1.1)
